{"poster":"/lgNXAQ1TlKEKzssbjcc5iEhs8mi.jpg","overview":"When a comet passes close to the earth, machines all over the world come alive and go on homicidal rampages. A group of people at a desolate truck stop are held hostage by a gang of homicidal 18-wheelers. The frightened people set out to defeat the killer machines ... or be killed by them.","genres":[28,18,27,878],"mdb_id":9980,"original_title":"Maximum Overdrive","title":"Maximum Overdrive","backdrop":"/jUrEJQ6tx48KTF47PdA9f1tAZy6.jpg","release_date":"1986-07-25","youtube_id":"DVigoLjor0Q","cast":["Emilio Estevez","Pat Hingle","Laura Harrington"],"directors":["Stephen King"],"runtime":97,"imdbId":"tt0091499"}