{"poster":"/5z1D8ggj0whtOgwXTTY3I4kqWhr.jpg","overview":"In this remake of the classic 50s SF tale, a boy tries to stop an invasion of his town by aliens who take over the the minds of his parents, his least-liked schoolteacher and other townspeople. With the aid of the school nurse the boy enlists the aid of the U.S. Marines.","genres":[878],"mdb_id":31909,"original_title":"Invaders from Mars","title":"Invaders from Mars","backdrop":"/nCJvpSUitSj7gl59zIiAnjx1H38.jpg","release_date":"1986-01-01","youtube_id":"hroKkAW6piI","cast":["Karen Black","Hunter Carson","Timothy Bottoms"],"directors":["Tobe Hooper"],"runtime":100,"imdbId":"tt0091276"}