{"poster":"/uYVheUBf8ITaocUP4Og9GXxOMIH.jpg","overview":"After a violent storm, a dense cloud of mist envelops a small Maine town, trapping artist David Drayton and his five-year-old son in a local grocery store with other people. They soon discover that the mist conceals deadly horrors that threaten their lives, and worse, their sanity.","genres":[878,27,53],"mdb_id":5876,"original_title":"The Mist","title":"The Mist","backdrop":"/xUYTWv2W3wCakBw4fOpTfFQ5e1I.jpg","release_date":"2007-11-21","youtube_id":"NgWY1_ck_RU"}