{"poster":"/4zZhl5uPCmLft5FrRHlglDxEhtA.jpg","overview":"An evil scientist implants the brain of Michael, a murdered high school student, in an animatronic Tyrannosaurus. He escapes, wreaks vengeance on his high school tormentors and is reunited with his sweetheart Tammy. Together, the couple try to elude the mad scientist and the police and find a more appropriate vessel for Michael's brain.","genres":[35,878],"mdb_id":55563,"original_title":"Tammy and the T-Rex","title":"Tammy and the T-Rex","backdrop":"/1cIpip90T6pnkR5VDYTqESS5TcD.jpg","release_date":"1994-12-28","youtube_id":"VFlKDUNeL5Y"}