{"poster":"/dq3PTFp0lLlEa2TnJepEknU2Sys.jpg","overview":"The true story about an honest New York cop who blew the whistle on rampant corruption in the force only to have his comrades turn against him.","genres":[80,18,36],"mdb_id":9040,"original_title":"Serpico","title":"Serpico","backdrop":"/6pHv9P9yNXvOAp6G9UU8W8wzeLR.jpg","release_date":"1973-12-05","youtube_id":"WMnzzhGwPk4","cast":["Al Pacino","John Randolph Jones","Jack Kehoe"],"directors":["Sidney Lumet"],"runtime":129,"imdbId":"tt0070666"}