{"poster":"/vVhjMqKamA8sfDruUd8amkc8RoD.jpg","overview":"Michael Paré stars as Eddie Wilson of the rock band Eddie and Cruisers. The band is at the height of their career in the 1960s when front man Eddie drives his car off a bridge in an apparent suicide -- but the body was never found.","genres":[18,10402],"mdb_id":21721,"original_title":"Eddie and the Cruisers","title":"Eddie and the Cruisers","backdrop":"/62nrfxlg58OTT53AlxTZlS73ech.jpg","release_date":"1983-09-23","youtube_id":"XnaCXCcYWEc","cast":["Tom Berenger","Michael Paré","Joe Pantoliano"],"directors":["Martin Davidson"],"runtime":95,"imdbId":"tt0085475"}